miniirc.py
miniirc-1.10.0.dist-info/LICENSE.md
miniirc-1.10.0.dist-info/METADATA
miniirc-1.10.0.dist-info/WHEEL
miniirc-1.10.0.dist-info/top_level.txt
miniirc-1.10.0.dist-info/RECORD
