Metadata-Version: 2.1
Name: miniirc
Version: 1.10.0
Summary: A lightweight IRC framework.
Home-page: https://github.com/luk3yx/miniirc
Author: luk3yx
License: MIT
Classifier: Intended Audience :: Developers
Classifier: Development Status :: 5 - Production/Stable
Classifier: License :: OSI Approved :: MIT License
Classifier: Operating System :: OS Independent
Classifier: Programming Language :: Python :: 3
Classifier: Programming Language :: Python :: 3.4
Classifier: Programming Language :: Python :: 3.5
Classifier: Programming Language :: Python :: 3.6
Classifier: Programming Language :: Python :: 3.7
Classifier: Programming Language :: Python :: 3.8
Classifier: Topic :: Software Development :: Libraries
Requires-Python: >=3.4
License-File: LICENSE.md
Requires-Dist: certifi>=2020.4.5.1
